{
  "version": "7",
  "dialect": "postgresql",
  "entries": [
    {
      "idx": 0,
      "version": "7",
      "when": 1763952657466,
      "tag": "0000_overconfident_doctor_spectrum",
      "breakpoints": true
    },
    {
      "idx": 1,
      "version": "7",
      "when": 1764116326913,
      "tag": "0001_strange_nuke",
      "breakpoints": true
    },
    {
      "idx": 2,
      "version": "7",
      "when": 1764153213671,
      "tag": "0002_thankful_unus",
      "breakpoints": true
    }
  ]
}
